MANIFEST.in
setup.py
supercaptcha/__init__.py
supercaptcha/settings.py
supercaptcha.egg-info/PKG-INFO
supercaptcha.egg-info/SOURCES.txt
supercaptcha.egg-info/dependency_links.txt
supercaptcha.egg-info/requires.txt
supercaptcha.egg-info/top_level.txt
supercaptcha/fonts/acidic.ttf
supercaptcha/fonts/boneca.ttf