Metadata-Version: 1.0
Name: supercaptcha
Version: 0.1.4
Summary: captchafield for django newforms
Home-page: UNKNOWN
Author: Viktor Kotseruba
Author-email: barbuzaster@gmail.com
License: MIT
Keywords: forms web django
Platform: UNKNOWN
